{
    "name": "radio",
    "description": "The radio services",
    "files": [
        "README.md",
        "shims.d.ts",
        "enums.d.ts",
        "radio.cpp",
        "radio.ts",
        "pins.ts",
        "ws2812SendBuffer.asm"
    ],
    "public": true,
    "dependencies": {
        "core": "file:../core"
    },
    "yotta": {
        "config": {
            "microbit-dal": {
                "bluetooth": {
                    "enabled": 0
                }
            }
        }
    }
}