{
    "name": "core",
    "description": "The microbit core library",
    "installedVersion": "tsmdvf",
    "files": [
        "README.md",
        "ManagedBuffer.cpp",
        "ManagedBuffer.h",
        "pxt.cpp",
        "pxt.h",
        "dal.d.ts",
        "enums.d.ts",
        "shims.d.ts",
        "pxt-core.d.ts",
        "core.cpp",
        "pxt-helpers.ts",
        "helpers.ts",
        "images.cpp",
        "basic.cpp",
        "icons.ts",
        "input.cpp",
        "input.ts",
        "control.ts",
        "control.cpp",
        "game.ts",
        "led.cpp",
        "led.ts",
        "music.ts",
        "melodies.ts",
        "pins.cpp",
        "pins.ts",
        "serial.cpp",
        "serial.ts",
        "buffer.cpp",
        "pxtparts.json",
        "parts/speaker.svg",
        "parts/headphone.svg",
        "_locales/ja/core-jsdoc-strings.json",
        "_locales/fr/core-jsdoc-strings.json",
        "_locales/fr/core-strings.json",
        "_locales/de/core-jsdoc-strings.json",
        "_locales/de/core-strings.json",
        "_locales/no/core-strings.json",
        "_locales/ja/core-strings.json",
        "_locales/sv-SE/core-jsdoc-strings.json",
        "_locales/no/core-jsdoc-strings.json",
        "_locales/si-LK/core-strings.json",
        "_locales/sv-SE/core-strings.json",
        "_locales/si-LK/core-jsdoc-strings.json",
        "_locales/nl/core-strings.json",
        "_locales/nl/core-jsdoc-strings.json",
        "_locales/fr-CA/core-strings.json",
        "_locales/hr/core-strings.json",
        "_locales/es-MX/core-strings.json",
        "_locales/ta/core-strings.json",
        "_locales/id/core-strings.json",
        "_locales/pt-BR/core-strings.json",
        "_locales/zh-TW/core-strings.json",
        "_locales/zh-CN/core-strings.json",
        "_locales/uk/core-strings.json",
        "_locales/tr/core-strings.json",
        "_locales/sl/core-strings.json",
        "_locales/sk/core-strings.json",
        "_locales/ru/core-strings.json",
        "_locales/pt-PT/core-strings.json",
        "_locales/pl/core-strings.json",
        "_locales/ko/core-strings.json",
        "_locales/it/core-strings.json",
        "_locales/hu/core-strings.json",
        "_locales/he/core-strings.json",
        "_locales/fi/core-strings.json",
        "_locales/el/core-strings.json",
        "_locales/da/core-strings.json",
        "_locales/cs/core-strings.json",
        "_locales/bg/core-strings.json",
        "_locales/ar/core-strings.json",
        "_locales/es-ES/core-strings.json",
        "_locales/fr-CA/core-jsdoc-strings.json",
        "_locales/hr/core-jsdoc-strings.json",
        "_locales/es-MX/core-jsdoc-strings.json",
        "_locales/ta/core-jsdoc-strings.json",
        "_locales/id/core-jsdoc-strings.json",
        "_locales/pt-BR/core-jsdoc-strings.json",
        "_locales/zh-TW/core-jsdoc-strings.json",
        "_locales/zh-CN/core-jsdoc-strings.json",
        "_locales/uk/core-jsdoc-strings.json",
        "_locales/tr/core-jsdoc-strings.json",
        "_locales/sl/core-jsdoc-strings.json",
        "_locales/sk/core-jsdoc-strings.json",
        "_locales/ru/core-jsdoc-strings.json",
        "_locales/pt-PT/core-jsdoc-strings.json",
        "_locales/pl/core-jsdoc-strings.json",
        "_locales/ko/core-jsdoc-strings.json",
        "_locales/it/core-jsdoc-strings.json",
        "_locales/hu/core-jsdoc-strings.json",
        "_locales/fi/core-jsdoc-strings.json",
        "_locales/el/core-jsdoc-strings.json",
        "_locales/da/core-jsdoc-strings.json",
        "_locales/cs/core-jsdoc-strings.json",
        "_locales/bg/core-jsdoc-strings.json",
        "_locales/ar/core-jsdoc-strings.json",
        "_locales/es-ES/core-jsdoc-strings.json"
    ],
    "public": true,
    "dependencies": {},
    "yotta": {
        "optionalConfig": {
            "microbit-dal": {
                "bluetooth": {
                    "private_addressing": 0,
                    "advertising_timeout": 0,
                    "tx_power": 6,
                    "dfu_service": 1,
                    "event_service": 1,
                    "device_info_service": 1,
                    "eddystone_url": 1,
                    "eddystone_uid": 1,
                    "open": 0,
                    "pairing_mode": 1,
                    "whitelist": 1,
                    "security_level": "SECURITY_MODE_ENCRYPTION_NO_MITM"
                }
            }
        }
    }
}